OsEasyControl/OEC.py
OsEasyControl/__init__.py
OsEasyControl-1.2.dist-info/METADATA
OsEasyControl-1.2.dist-info/WHEEL
OsEasyControl-1.2.dist-info/top_level.txt
OsEasyControl-1.2.dist-info/RECORD
