Metadata-Version: 2.1
Name: OsEasyControl
Version: 1.2
Summary: Easy to use cmd in py
Home-page: UNKNOWN
Author: 자색치즈고구마
Author-email: s.potato0530@gmail.com
License: UNKNOWN
Keywords: OsEasyControl
Platform: UNKNOWN
Requires-Python: >=3.3
